{
  "modified": "Tue Nov 03 2020 09:43:38 GMT+0800 (CST)",
  "width": 356,
  "height": 160,
  "comps": [
    {
      "type": "trapezoid",
      "background": "#D8D8D8",
      "borderWidth": 0.5,
      "borderColor": "rgb(0,0,0)",
      "borderJoin": "miter",
      "gradient": "spread.horizontal",
      "borderWidthAbsolute": true,
      "rotation": 4.71239,
      "rect": [
        101,
        -19.5,
        159,
        200
      ]
    },
    {
      "type": "rect",
      "background": "#D8D8D8",
      "borderWidth": 0.5,
      "borderColor": "rgb(0,0,0)",
      "borderJoin": "miter",
      "gradient": "spread.vertical",
      "borderWidthAbsolute": true,
      "rect": [
        0.5,
        70.5,
        80,
        20
      ]
    },
    {
      "type": "rect",
      "background": "#D8D8D8",
      "borderWidth": 0.5,
      "borderColor": "rgb(0,0,0)",
      "borderJoin": "miter",
      "gradient": "spread.vertical",
      "borderWidthAbsolute": true,
      "rect": [
        280.5,
        70.5,
        75,
        20
      ]
    },
    {
      "type": "rect",
      "background": "#D8D8D8",
      "borderWidth": 0.5,
      "borderColor": "rgb(0,0,0)",
      "borderJoin": "miter",
      "gradient": "spread.vertical",
      "borderWidthAbsolute": true,
      "rect": [
        58.35469,
        65,
        10,
        30
      ]
    },
    {
      "type": "rect",
      "background": "#D8D8D8",
      "borderWidth": 0.5,
      "borderColor": "rgb(0,0,0)",
      "borderJoin": "miter",
      "gradient": "spread.vertical",
      "borderWidthAbsolute": true,
      "rect": [
        33.64257,
        65,
        10,
        30
      ]
    },
    {
      "type": "rect",
      "background": "#D8D8D8",
      "borderWidth": 0.5,
      "borderColor": "rgb(0,0,0)",
      "borderJoin": "miter",
      "gradient": "spread.vertical",
      "borderWidthAbsolute": true,
      "rect": [
        8.93045,
        65,
        10,
        30
      ]
    },
    {
      "type": "rect",
      "background": "#D8D8D8",
      "borderWidth": 0.5,
      "borderColor": "rgb(0,0,0)",
      "borderJoin": "miter",
      "gradient": "spread.vertical",
      "borderWidthAbsolute": true,
      "rect": [
        294.15017,
        65,
        10,
        30
      ]
    },
    {
      "type": "rect",
      "background": "#D8D8D8",
      "borderWidth": 0.5,
      "borderColor": "rgb(0,0,0)",
      "borderJoin": "miter",
      "gradient": "spread.vertical",
      "borderWidthAbsolute": true,
      "rect": [
        325.5,
        65,
        10,
        30
      ]
    }
  ]
}